gee_zonal/__init__.py
gee_zonal/catalog.py
gee_zonal/gee_helpers.py
gee_zonal/zonalstats.py
gee_zonal/custom/landsat.py
gee_zonal/custom/modis.py
gee_zonal/custom/tsinghua.py
gee_zonal-0.1.2.dist-info/licenses/LICENSE.md
gee_zonal-0.1.2.dist-info/METADATA
gee_zonal-0.1.2.dist-info/WHEEL
gee_zonal-0.1.2.dist-info/top_level.txt
gee_zonal-0.1.2.dist-info/RECORD
