Metadata-Version: 2.4
Name: gee_zonal
Version: 0.1.2
Summary: Wrapper function to request temporal and zonal statistics from Google Earth Engine
Author-email: Development Data Group <github@worldbank.org>
Maintainer-email: Andres Chamorro <achamorroelizond@worldbank.org>
License: World Bank Master Community License Agreement
Project-URL: Homepage, https://github.com/worldbank/GEE_Zonal
Project-URL: Bug Reports, https://github.com/worldbank/GEE_Zonal/issues
Project-URL: Source, https://github.com/worldbank/GEE_Zonal
Keywords: zonal statistics,gee,earth engine
Classifier: Programming Language :: Python :: 3
Classifier: Programming Language :: Python :: 3.7
Classifier: Programming Language :: Python :: 3.8
Classifier: Programming Language :: Python :: 3.9
Classifier: Programming Language :: Python :: 3.10
Classifier: Programming Language :: Python :: 3.11
Classifier: Programming Language :: Python :: 3 :: Only
Classifier: Development Status :: 3 - Alpha
Classifier: Intended Audience :: Developers
Classifier: Operating System :: OS Independent
Requires-Python: >=3.7
License-File: LICENSE.md
Requires-Dist: earthengine-api>=0.1.342
Requires-Dist: pandas>=1.2.2
Requires-Dist: geopandas>=0.12.2
Requires-Dist: geojson
Provides-Extra: notebook
Requires-Dist: notebook>=6.5.2; extra == "notebook"
Dynamic: license-file
